SW/SW.py
SW/__init__.py
SW_transformation-0.0.2.dist-info/LICENSE
SW_transformation-0.0.2.dist-info/METADATA
SW_transformation-0.0.2.dist-info/WHEEL
SW_transformation-0.0.2.dist-info/top_level.txt
SW_transformation-0.0.2.dist-info/RECORD
