Metadata-Version: 2.1
Name: SW-transformation
Version: 0.0.2
Summary: A fast classifier for binary node classification in bipartite graphs
Home-page: https://github.com/SPraet/SW-transformation
Author: Stiene Praet
Author-email: stiene.praet@uantwerp.be
License: UNKNOWN
Platform: UNKNOWN
Classifier: Programming Language :: Python :: 3
Classifier: License :: OSI Approved :: MIT License
Classifier: Operating System :: OS Independent
